smmpy.py
smmpy-0.1.0.dist-info/METADATA
smmpy-0.1.0.dist-info/WHEEL
smmpy-0.1.0.dist-info/top_level.txt
smmpy-0.1.0.dist-info/RECORD
