Metadata-Version: 2.4
Name: smmpy
Version: 0.1.0
Summary: A Python client for SMM panels
Home-page: https://github.com/sleepyvani/smmpy
Author: sleepyvani
Author-email: vanixjnk@gmail.com
Classifier: Programming Language :: Python :: 3
Classifier: License :: OSI Approved :: MIT License
Classifier: Operating System :: OS Independent
Requires-Python: >=3.6
Requires-Dist: requests
Dynamic: author
Dynamic: author-email
Dynamic: classifier
Dynamic: description
Dynamic: description-content-type
Dynamic: home-page
Dynamic: requires-dist
Dynamic: requires-python
Dynamic: summary
